mypack/__init__.py
mypack/np_utils.py
mypack/pd_utils.py
mypack/plot_utils.py
tests/__init__.py
tests/test_lib.py
leandro-0.0.1.dist-info/LICENSE
leandro-0.0.1.dist-info/METADATA
leandro-0.0.1.dist-info/WHEEL
leandro-0.0.1.dist-info/top_level.txt
leandro-0.0.1.dist-info/RECORD
